setup.py
sujmarkov/__init__.py
sujmarkov/__main__.py
sujmarkov/tests.py
sujmarkov.egg-info/PKG-INFO
sujmarkov.egg-info/SOURCES.txt
sujmarkov.egg-info/dependency_links.txt
sujmarkov.egg-info/requires.txt
sujmarkov.egg-info/top_level.txt