Metadata-Version: 1.0
Name: sujmarkov
Version: 1.0.0
Summary: A markov generator
Home-page: https://github.com/sujaymansingh/sujmarkov
Author: Sujay Mansingh
Author-email: sujay.mansingh@gmail.com
License: LICENSE.txt
Platform: UNKNOWN
